src/teal_lang/dist_data/teal_lambda.zip
teal_lang/__init__.py
teal_lang/cli/__init__.py
teal_lang/cli/hosted_query.py
teal_lang/cli/in_hosted.py
teal_lang/cli/in_own.py
teal_lang/cli/interface.py
teal_lang/cli/main.py
teal_lang/cli/utils.py
teal_lang/cloud/__init__.py
teal_lang/cloud/api.py
teal_lang/cloud/aws.py
teal_lang/config.py
teal_lang/config_classes.py
teal_lang/controllers/__init__.py
teal_lang/controllers/ddb.py
teal_lang/controllers/ddb_model.py
teal_lang/controllers/local.py
teal_lang/dist_data/teal.toml
teal_lang/dist_data/teal_lambda.zip
teal_lang/exceptions.py
teal_lang/executors/__init__.py
teal_lang/executors/awslambda.py
teal_lang/executors/multiprocess.py
teal_lang/executors/thread.py
teal_lang/load.py
teal_lang/machine/__init__.py
teal_lang/machine/arec.py
teal_lang/machine/controller.py
teal_lang/machine/executable.py
teal_lang/machine/foreign.py
teal_lang/machine/future.py
teal_lang/machine/instruction.py
teal_lang/machine/instructionset.py
teal_lang/machine/machine.py
teal_lang/machine/probe.py
teal_lang/machine/state.py
teal_lang/machine/stdout_item.py
teal_lang/machine/teal_serialisable.py
teal_lang/machine/thread_failure.py
teal_lang/machine/types.py
teal_lang/run/__init__.py
teal_lang/run/aws.py
teal_lang/run/common.py
teal_lang/run/dynamodb.py
teal_lang/run/lambda_handlers.py
teal_lang/run/local.py
teal_lang/teal_compiler/__init__.py
teal_lang/teal_compiler/attributes.py
teal_lang/teal_compiler/compiler.py
teal_lang/teal_parser/__init__.py
teal_lang/teal_parser/nodes.py
teal_lang/teal_parser/parser.py
teal_lang/teal_parser/repls.py
teal_lang-0.4.3.dist-info/entry_points.txt
teal_lang-0.4.3.dist-info/LICENSE
teal_lang-0.4.3.dist-info/WHEEL
teal_lang-0.4.3.dist-info/METADATA
teal_lang-0.4.3.dist-info/RECORD
